normalize_filenames/__init__.py
normalize_filenames/normf.py
normalize_filenames-0.6.0.dist-info/METADATA
normalize_filenames-0.6.0.dist-info/WHEEL
normalize_filenames-0.6.0.dist-info/entry_points.txt
normalize_filenames-0.6.0.dist-info/RECORD
